numpydoctor/__init__.py
numpydoctor/__main__.py
numpydoctor/application.py
numpydoctor/ast_tools.py
numpydoctor/docstring_tools.py
numpydoctor/type_tools.py
numpydoctor-1.1.dist-info/LICENSE
numpydoctor-1.1.dist-info/METADATA
numpydoctor-1.1.dist-info/WHEEL
numpydoctor-1.1.dist-info/entry_points.txt
numpydoctor-1.1.dist-info/top_level.txt
numpydoctor-1.1.dist-info/RECORD
